qetools/__init__.py
qetools/qetools.py
qetools/pseudos/LDA_ONCV/Ag.UPF
qetools/pseudos/LDA_ONCV/Al.UPF
qetools/pseudos/LDA_ONCV/Ar.UPF
qetools/pseudos/LDA_ONCV/As.UPF
qetools/pseudos/LDA_ONCV/Au.UPF
qetools/pseudos/LDA_ONCV/B.UPF
qetools/pseudos/LDA_ONCV/Ba.UPF
qetools/pseudos/LDA_ONCV/Be.UPF
qetools/pseudos/LDA_ONCV/Bi.UPF
qetools/pseudos/LDA_ONCV/Br.UPF
qetools/pseudos/LDA_ONCV/C.UPF
qetools/pseudos/LDA_ONCV/Ca.UPF
qetools/pseudos/LDA_ONCV/Cd.UPF
qetools/pseudos/LDA_ONCV/Cl.UPF
qetools/pseudos/LDA_ONCV/Co.UPF
qetools/pseudos/LDA_ONCV/Cr.UPF
qetools/pseudos/LDA_ONCV/Cs.UPF
qetools/pseudos/LDA_ONCV/Cu.UPF
qetools/pseudos/LDA_ONCV/F.UPF
qetools/pseudos/LDA_ONCV/Fe.UPF
qetools/pseudos/LDA_ONCV/Ga.UPF
qetools/pseudos/LDA_ONCV/Ge.UPF
qetools/pseudos/LDA_ONCV/H.UPF
qetools/pseudos/LDA_ONCV/He.UPF
qetools/pseudos/LDA_ONCV/Hf.UPF
qetools/pseudos/LDA_ONCV/Hg.UPF
qetools/pseudos/LDA_ONCV/I.UPF
qetools/pseudos/LDA_ONCV/In.UPF
qetools/pseudos/LDA_ONCV/Ir.UPF
qetools/pseudos/LDA_ONCV/K.UPF
qetools/pseudos/LDA_ONCV/Kr.UPF
qetools/pseudos/LDA_ONCV/Li.UPF
qetools/pseudos/LDA_ONCV/Mg.UPF
qetools/pseudos/LDA_ONCV/Mn.UPF
qetools/pseudos/LDA_ONCV/Mo.UPF
qetools/pseudos/LDA_ONCV/N.UPF
qetools/pseudos/LDA_ONCV/Na.UPF
qetools/pseudos/LDA_ONCV/Nb.UPF
qetools/pseudos/LDA_ONCV/Ne.UPF
qetools/pseudos/LDA_ONCV/Ni.UPF
qetools/pseudos/LDA_ONCV/O.UPF
qetools/pseudos/LDA_ONCV/Os.UPF
qetools/pseudos/LDA_ONCV/P.UPF
qetools/pseudos/LDA_ONCV/Pb.UPF
qetools/pseudos/LDA_ONCV/Pd.UPF
qetools/pseudos/LDA_ONCV/Po.UPF
qetools/pseudos/LDA_ONCV/Pt.UPF
qetools/pseudos/LDA_ONCV/Rb.UPF
qetools/pseudos/LDA_ONCV/Re.UPF
qetools/pseudos/LDA_ONCV/Rh.UPF
qetools/pseudos/LDA_ONCV/Rn.UPF
qetools/pseudos/LDA_ONCV/Ru.UPF
qetools/pseudos/LDA_ONCV/S.UPF
qetools/pseudos/LDA_ONCV/Sb.UPF
qetools/pseudos/LDA_ONCV/Sc.UPF
qetools/pseudos/LDA_ONCV/Se.UPF
qetools/pseudos/LDA_ONCV/Si.UPF
qetools/pseudos/LDA_ONCV/Sn.UPF
qetools/pseudos/LDA_ONCV/Sr.UPF
qetools/pseudos/LDA_ONCV/Ta.UPF
qetools/pseudos/LDA_ONCV/Tc.UPF
qetools-1.1.1.dist-info/LICENCE
qetools-1.1.1.dist-info/METADATA
qetools-1.1.1.dist-info/WHEEL
qetools-1.1.1.dist-info/entry_points.txt
qetools-1.1.1.dist-info/top_level.txt
qetools-1.1.1.dist-info/RECORD
