Metadata-Version: 2.1
Name: qetools
Version: 1.1.1
Summary: A command line helper for QuantumEspresso calculations
Home-page: UNKNOWN
Author: Harish PVV
Author-email: harishpvv@gmail.com
License: MIT
Keywords: quantum espresso dft harishpvv
Platform: UNKNOWN
Classifier: Programming Language :: Python :: 3
Classifier: License :: OSI Approved :: MIT License
Classifier: Operating System :: OS Independent
Requires-Python: >=3.6
Requires-Dist: ase
Requires-Dist: matplotlib
Requires-Dist: numpy
